metaflow_extensions/deepspeed/plugins/az_store.py
metaflow_extensions/deepspeed/plugins/hf_callbacks.py
metaflow_extensions/deepspeed/plugins/mfextinit_deepspeed.py
metaflow_extensions/deepspeed/plugins/deepspeed_libs/__init__.py
metaflow_extensions/deepspeed/plugins/deepspeed_libs/constants.py
metaflow_extensions/deepspeed/plugins/deepspeed_libs/datastore.py
metaflow_extensions/deepspeed/plugins/deepspeed_libs/deepspeed_decorator.py
metaflow_extensions/deepspeed/plugins/deepspeed_libs/exceptions.py
metaflow_extensions/deepspeed/plugins/deepspeed_libs/executor.py
metaflow_extensions/deepspeed/plugins/deepspeed_libs/mpi_setup.py
metaflow_extensions/deepspeed/plugins/deepspeed_libs/status_notifier.py
metaflow_extensions/deepspeed/plugins/deepspeed_libs/card_utilities/__init__.py
metaflow_extensions/deepspeed/plugins/deepspeed_libs/card_utilities/async_cards.py
metaflow_extensions/deepspeed/plugins/deepspeed_libs/card_utilities/extra_components.py
metaflow_extensions/deepspeed/plugins/deepspeed_libs/card_utilities/injector.py
metaflow_extensions/deepspeed/plugins/deepspeed_libs/hugging_face/__init__.py
metaflow_extensions/deepspeed/plugins/deepspeed_libs/hugging_face/card_callback.py
metaflow_extensions/deepspeed/plugins/deepspeed_libs/hugging_face/card_decorator.py
metaflow_extensions/deepspeed/plugins/deepspeed_libs/hugging_face/constants.py
metaflow_extensions/deepspeed/toplevel/__init__.py
metaflow_extensions/deepspeed/toplevel/toplevel.py
metaflow_deepspeed-0.0.9.dist-info/LICENSE
metaflow_deepspeed-0.0.9.dist-info/METADATA
metaflow_deepspeed-0.0.9.dist-info/WHEEL
metaflow_deepspeed-0.0.9.dist-info/top_level.txt
metaflow_deepspeed-0.0.9.dist-info/RECORD
