Metadata-Version: 2.1
Name: metaflow-deepspeed
Version: 0.0.9
Summary: An EXPERIMENTAL Deepspeed decorator for Metaflow
Author: Eddie Mattia
Author-email: eddie@outerbounds.com
License-File: LICENSE
